sigma/__init__.py
sigma/gui/__init__.py
sigma/gui/gui.py
sigma/models/__init__.py
sigma/models/autoencoder.py
sigma/src/__init__.py
sigma/src/dim_reduction.py
sigma/src/segmentation.py
sigma/src/utils.py
sigma/utils/__init__.py
sigma/utils/load.py
sigma/utils/loadtem.py
sigma/utils/normalisation.py
sigma/utils/visualisation.py
emsigma-0.1.26.dist-info/LICENSE
emsigma-0.1.26.dist-info/METADATA
emsigma-0.1.26.dist-info/WHEEL
emsigma-0.1.26.dist-info/top_level.txt
emsigma-0.1.26.dist-info/RECORD
