Metadata-Version: 2.1
Name: emsigma
Version: 0.1.26
Summary: spectral interpretation using gaussian mixtures and autoencoder 
Home-page: https://github.com/poyentung/sigma
Author: Po-Yen Tung
Author-email: pyt21@cam.ac.uk
License: GNU GPLv3
Keywords: hyperspectral imaging analysis,energy dispersive x-ray spectroscopy,scanning electron microscopy,gaussain mixture,autoencoder,non-negative matrix factorization
Platform: UNKNOWN
Classifier: Programming Language :: Python :: 3
Classifier: Programming Language :: Python :: 3.7
Classifier: Intended Audience :: Science/Research
Classifier: License :: OSI Approved :: GNU General Public License v3 (GPLv3)
Classifier: Natural Language :: English
Classifier: Operating System :: OS Independent
Classifier: Topic :: Software Development :: Libraries :: Python Modules
Classifier: Topic :: Scientific/Engineering
Requires-Python: >=3.7
License-File: LICENSE
Requires-Dist: notebook
Requires-Dist: torch (>=1.10.0+cu111)
Requires-Dist: hyperspy (>=1.6.5)
Requires-Dist: ipywidgets
Requires-Dist: lmfit (>=0.9.12)
Requires-Dist: matplotlib (>=3.2.2)
Requires-Dist: numba
Requires-Dist: numpy (>=1.19.5)
Requires-Dist: scikit-learn (>=1.0.2)
Requires-Dist: scipy
Requires-Dist: tqdm (>=4.62.3)
Requires-Dist: seaborn (>=0.11.2)
Requires-Dist: plotly (>=4.4.1)
Requires-Dist: altair (>=4.2.0)
